LICENSE
README.md
pyproject.toml
setup.cfg
setup.py
in1/__init__.py
in1/batch.py
in1/dataset.py
in1/exceptions.py
in1/inference.py
in1/io.py
in1/sisr.py
in1.egg-info/PKG-INFO
in1.egg-info/SOURCES.txt
in1.egg-info/dependency_links.txt
in1.egg-info/entry_points.txt
in1.egg-info/requires.txt
in1.egg-info/top_level.txt
in1/bin/__init__.py
in1/bin/commands.py
in1/bin/parser.py