Metadata-Version: 2.1
Name: in1
Version: 2.0.1
Summary: Sobolt's client for in1.
Home-page: https://in1.ai
Author: Sobolt
Author-email: info@sobolt.com
License: MIT
Platform: UNKNOWN
Classifier: Programming Language :: Python :: 3
Classifier: Programming Language :: Python :: 3 :: Only
Classifier: Programming Language :: Python :: 3.6
Classifier: Programming Language :: Python :: 3.7
Classifier: Programming Language :: Python :: 3.8
Requires-Python: >=3.6
